{
  "a_comp_cor_00": {
    "CumulativeVarianceExplained": 0.0793405167,
    "Mask": "combined",
    "Method": "aCompCor",
    "Retained": true,
    "SingularValue": 181.4243920854,
    "VarianceExplained": 0.0793405167
  },
  "a_comp_cor_01": {
    "CumulativeVarianceExplained": 0.1114234246,
    "Mask": "combined",
    "Method": "aCompCor",
    "Retained": true,
    "SingularValue": 115.3679104854,
    "VarianceExplained": 0.0320829079
  },
  "a_comp_cor_02": {
    "CumulativeVarianceExplained": 0.1376125735,
    "Mask": "combined",
    "Method": "aCompCor",
    "Retained": true,
    "SingularValue": 104.2338685864,
    "VarianceExplained": 0.0261891489
  },
  "a_comp_cor_03": {
    "CumulativeVarianceExplained": 0.1594866326,
    "Mask": "combined",
    "Method": "aCompCor",
    "Retained": true,
    "SingularValue": 95.2604996473,
    "VarianceExplained": 0.0218740591
  },
  "a_comp_cor_04": {
    "CumulativeVarianceExplained": 0.1804239762,
    "Mask": "combined",
    "Method": "aCompCor",
    "Retained": true,
    "SingularValue": 93.1985068949,
    "VarianceExplained": 0.0209373436
  },
  "a_comp_cor_05": {
    "CumulativeVarianceExplained": 0.1964881291,
    "Mask": "combined",
    "Method": "aCompCor",
    "Retained": true,
    "SingularValue": 81.6351281355,
    "VarianceExplained": 0.0160641529
  },
  "a_comp_cor_06": {
    "CumulativeVarianceExplained": 0.2117207416,
    "Mask": "combined",
    "Method": "aCompCor",
    "Retained": true,
    "SingularValue": 79.4941849914,
    "VarianceExplained": 0.0152326125
  },
  "a_comp_cor_07": {
    "CumulativeVarianceExplained": 0.2250600505,
    "Mask": "combined",
    "Method": "aCompCor",
    "Retained": true,
    "SingularValue": 74.3900465126,
    "VarianceExplained": 0.013339309
  },
  "a_comp_cor_08": {
    "CumulativeVarianceExplained": 0.237166645,
    "Mask": "combined",
    "Method": "aCompCor",
    "Retained": true,
    "SingularValue": 70.8694662022,
    "VarianceExplained": 0.0121065944
  },
  "a_comp_cor_09": {
    "CumulativeVarianceExplained": 0.2489547174,
    "Mask": "combined",
    "Method": "aCompCor",
    "Retained": true,
    "SingularValue": 69.9309716506,
    "VarianceExplained": 0.0117880724
  },
  "a_comp_cor_10": {
    "CumulativeVarianceExplained": 0.2602619842,
    "Mask": "combined",
    "Method": "aCompCor",
    "Retained": true,
    "SingularValue": 68.4899711489,
    "VarianceExplained": 0.0113072668
  },
  "a_comp_cor_11": {
    "CumulativeVarianceExplained": 0.2714105492,
    "Mask": "combined",
    "Method": "aCompCor",
    "Retained": true,
    "SingularValue": 68.0076314415,
    "VarianceExplained": 0.011148565
  },
  "a_comp_cor_12": {
    "CumulativeVarianceExplained": 0.2821804087,
    "Mask": "combined",
    "Method": "aCompCor",
    "Retained": true,
    "SingularValue": 66.84257673,
    "VarianceExplained": 0.0107698595
  },
  "a_comp_cor_13": {
    "CumulativeVarianceExplained": 0.2927882782,
    "Mask": "combined",
    "Method": "aCompCor",
    "Retained": true,
    "SingularValue": 66.3379806967,
    "VarianceExplained": 0.0106078695
  },
  "a_comp_cor_14": {
    "CumulativeVarianceExplained": 0.303334825,
    "Mask": "combined",
    "Method": "aCompCor",
    "Retained": true,
    "SingularValue": 66.1459574181,
    "VarianceExplained": 0.0105465468
  },
  "a_comp_cor_15": {
    "CumulativeVarianceExplained": 0.3135816229,
    "Mask": "combined",
    "Method": "aCompCor",
    "Retained": true,
    "SingularValue": 65.1991976089,
    "VarianceExplained": 0.010246798
  },
  "a_comp_cor_16": {
    "CumulativeVarianceExplained": 0.3236636125,
    "Mask": "combined",
    "Method": "aCompCor",
    "Retained": true,
    "SingularValue": 64.6727437112,
    "VarianceExplained": 0.0100819896
  },
  "a_comp_cor_17": {
    "CumulativeVarianceExplained": 0.3334217842,
    "Mask": "combined",
    "Method": "aCompCor",
    "Retained": true,
    "SingularValue": 63.6256735024,
    "VarianceExplained": 0.0097581717
  },
  "a_comp_cor_18": {
    "CumulativeVarianceExplained": 0.3431104405,
    "Mask": "combined",
    "Method": "aCompCor",
    "Retained": true,
    "SingularValue": 63.3986396835,
    "VarianceExplained": 0.0096886563
  },
  "a_comp_cor_19": {
    "CumulativeVarianceExplained": 0.3525753386,
    "Mask": "combined",
    "Method": "aCompCor",
    "Retained": true,
    "SingularValue": 62.6622715036,
    "VarianceExplained": 0.009464898
  },
  "a_comp_cor_20": {
    "CumulativeVarianceExplained": 0.3619282677,
    "Mask": "combined",
    "Method": "aCompCor",
    "Retained": true,
    "SingularValue": 62.2905243624,
    "VarianceExplained": 0.0093529292
  },
  "a_comp_cor_21": {
    "CumulativeVarianceExplained": 0.3711063721,
    "Mask": "combined",
    "Method": "aCompCor",
    "Retained": true,
    "SingularValue": 61.7056116455,
    "VarianceExplained": 0.0091781044
  },
  "a_comp_cor_22": {
    "CumulativeVarianceExplained": 0.3801552858,
    "Mask": "combined",
    "Method": "aCompCor",
    "Retained": true,
    "SingularValue": 61.2697894264,
    "VarianceExplained": 0.0090489137
  },
  "a_comp_cor_23": {
    "CumulativeVarianceExplained": 0.3889645579,
    "Mask": "combined",
    "Method": "aCompCor",
    "Retained": true,
    "SingularValue": 60.4530441668,
    "VarianceExplained": 0.008809272
  },
  "a_comp_cor_24": {
    "CumulativeVarianceExplained": 0.3976963889,
    "Mask": "combined",
    "Method": "aCompCor",
    "Retained": true,
    "SingularValue": 60.1867406231,
    "VarianceExplained": 0.008731831
  },
  "a_comp_cor_25": {
    "CumulativeVarianceExplained": 0.406403964,
    "Mask": "combined",
    "Method": "aCompCor",
    "Retained": true,
    "SingularValue": 60.1030871175,
    "VarianceExplained": 0.0087075751
  },
  "a_comp_cor_26": {
    "CumulativeVarianceExplained": 0.4150470359,
    "Mask": "combined",
    "Method": "aCompCor",
    "Retained": true,
    "SingularValue": 59.8800602152,
    "VarianceExplained": 0.0086430719
  },
  "a_comp_cor_27": {
    "CumulativeVarianceExplained": 0.4235436929,
    "Mask": "combined",
    "Method": "aCompCor",
    "Retained": true,
    "SingularValue": 59.3707052438,
    "VarianceExplained": 0.008496657
  },
  "a_comp_cor_28": {
    "CumulativeVarianceExplained": 0.43200104,
    "Mask": "combined",
    "Method": "aCompCor",
    "Retained": true,
    "SingularValue": 59.2332060242,
    "VarianceExplained": 0.008457347
  },
  "a_comp_cor_29": {
    "CumulativeVarianceExplained": 0.4403738529,
    "Mask": "combined",
    "Method": "aCompCor",
    "Retained": true,
    "SingularValue": 58.9364343653,
    "VarianceExplained": 0.0083728129
  },
  "a_comp_cor_30": {
    "CumulativeVarianceExplained": 0.448687326,
    "Mask": "combined",
    "Method": "aCompCor",
    "Retained": true,
    "SingularValue": 58.7272158924,
    "VarianceExplained": 0.0083134731
  },
  "a_comp_cor_31": {
    "CumulativeVarianceExplained": 0.4568159252,
    "Mask": "combined",
    "Method": "aCompCor",
    "Retained": true,
    "SingularValue": 58.0705609271,
    "VarianceExplained": 0.0081285993
  },
  "a_comp_cor_32": {
    "CumulativeVarianceExplained": 0.4648814362,
    "Mask": "combined",
    "Method": "aCompCor",
    "Retained": true,
    "SingularValue": 57.8447713784,
    "VarianceExplained": 0.008065511
  },
  "a_comp_cor_33": {
    "CumulativeVarianceExplained": 0.472870444,
    "Mask": "combined",
    "Method": "aCompCor",
    "Retained": true,
    "SingularValue": 57.56978205,
    "VarianceExplained": 0.0079890077
  },
  "a_comp_cor_34": {
    "CumulativeVarianceExplained": 0.4807283027,
    "Mask": "combined",
    "Method": "aCompCor",
    "Retained": true,
    "SingularValue": 57.0952885273,
    "VarianceExplained": 0.0078578587
  },
  "a_comp_cor_35": {
    "CumulativeVarianceExplained": 0.4885660048,
    "Mask": "combined",
    "Method": "aCompCor",
    "Retained": true,
    "SingularValue": 57.0220123485,
    "VarianceExplained": 0.0078377021
  },
  "a_comp_cor_36": {
    "CumulativeVarianceExplained": 0.4963653739,
    "Mask": "combined",
    "Method": "aCompCor",
    "Retained": true,
    "SingularValue": 56.8823985569,
    "VarianceExplained": 0.0077993691
  },
  "a_comp_cor_37": {
    "CumulativeVarianceExplained": 0.5040460555,
    "Mask": "combined",
    "Method": "aCompCor",
    "Retained": true,
    "SingularValue": 56.4479333846,
    "VarianceExplained": 0.0076806816
  },
  "aroma_motion_1": {
    "CSFFraction": 0.03,
    "EdgeFraction": 0.96,
    "HighFrequencyContent": 0.63,
    "MaximumRpCorrelation": 0.83,
    "Method": {
      "Name": "ICA-AROMA",
      "Version": "0.4.5"
    },
    "ModelVarianceExplained": 0.077973049,
    "MotionNoise": true,
    "TotalVarianceExplained": 0.0550078456
  },
  "aroma_motion_10": {
    "CSFFraction": 0.26,
    "EdgeFraction": 0.6,
    "HighFrequencyContent": 0.2,
    "MaximumRpCorrelation": 0.25,
    "Method": {
      "Name": "ICA-AROMA",
      "Version": "0.4.5"
    },
    "ModelVarianceExplained": 0.0396114665,
    "MotionNoise": true,
    "TotalVarianceExplained": 0.0279448022
  },
  "aroma_motion_11": {
    "CSFFraction": 0.02,
    "EdgeFraction": 0.32,
    "HighFrequencyContent": 0.14,
    "MaximumRpCorrelation": 0.42,
    "Method": {
      "Name": "ICA-AROMA",
      "Version": "0.4.5"
    },
    "ModelVarianceExplained": 0.0393343679,
    "MotionNoise": false,
    "TotalVarianceExplained": 0.0277493168
  },
  "aroma_motion_12": {
    "CSFFraction": 0.08,
    "EdgeFraction": 0.44,
    "HighFrequencyContent": 0.08,
    "MaximumRpCorrelation": 0.53,
    "Method": {
      "Name": "ICA-AROMA",
      "Version": "0.4.5"
    },
    "ModelVarianceExplained": 0.0384347926,
    "MotionNoise": false,
    "TotalVarianceExplained": 0.0271146911
  },
  "aroma_motion_13": {
    "CSFFraction": 0.04,
    "EdgeFraction": 0.54,
    "HighFrequencyContent": 0.63,
    "MaximumRpCorrelation": 0.46,
    "Method": {
      "Name": "ICA-AROMA",
      "Version": "0.4.5"
    },
    "ModelVarianceExplained": 0.0377965161,
    "MotionNoise": true,
    "TotalVarianceExplained": 0.0266644045
  },
  "aroma_motion_14": {
    "CSFFraction": 0.02,
    "EdgeFraction": 0.3,
    "HighFrequencyContent": 0.34,
    "MaximumRpCorrelation": 0.34,
    "Method": {
      "Name": "ICA-AROMA",
      "Version": "0.4.5"
    },
    "ModelVarianceExplained": 0.0360581889,
    "MotionNoise": false,
    "TotalVarianceExplained": 0.0254380624
  },
  "aroma_motion_15": {
    "CSFFraction": 0.0,
    "EdgeFraction": 0.56,
    "HighFrequencyContent": 0.14,
    "MaximumRpCorrelation": 0.25,
    "Method": {
      "Name": "ICA-AROMA",
      "Version": "0.4.5"
    },
    "ModelVarianceExplained": 0.0354557739,
    "MotionNoise": false,
    "TotalVarianceExplained": 0.0250130751
  },
  "aroma_motion_16": {
    "CSFFraction": 0.07,
    "EdgeFraction": 0.5,
    "HighFrequencyContent": 0.22,
    "MaximumRpCorrelation": 0.6,
    "Method": {
      "Name": "ICA-AROMA",
      "Version": "0.4.5"
    },
    "ModelVarianceExplained": 0.0348136545,
    "MotionNoise": false,
    "TotalVarianceExplained": 0.0245600776
  },
  "aroma_motion_17": {
    "CSFFraction": 0.04,
    "EdgeFraction": 0.33,
    "HighFrequencyContent": 0.49,
    "MaximumRpCorrelation": 0.43,
    "Method": {
      "Name": "ICA-AROMA",
      "Version": "0.4.5"
    },
    "ModelVarianceExplained": 0.0337805116,
    "MotionNoise": true,
    "TotalVarianceExplained": 0.0238312236
  },
  "aroma_motion_18": {
    "CSFFraction": 0.03,
    "EdgeFraction": 0.26,
    "HighFrequencyContent": 0.39,
    "MaximumRpCorrelation": 0.48,
    "Method": {
      "Name": "ICA-AROMA",
      "Version": "0.4.5"
    },
    "ModelVarianceExplained": 0.0335453184,
    "MotionNoise": true,
    "TotalVarianceExplained": 0.0236653012
  },
  "aroma_motion_19": {
    "CSFFraction": 0.0,
    "EdgeFraction": 0.43,
    "HighFrequencyContent": 0.17,
    "MaximumRpCorrelation": 0.39,
    "Method": {
      "Name": "ICA-AROMA",
      "Version": "0.4.5"
    },
    "ModelVarianceExplained": 0.0321371238,
    "MotionNoise": false,
    "TotalVarianceExplained": 0.0226718586
  },
  "aroma_motion_2": {
    "CSFFraction": 0.02,
    "EdgeFraction": 0.73,
    "HighFrequencyContent": 0.63,
    "MaximumRpCorrelation": 0.7,
    "Method": {
      "Name": "ICA-AROMA",
      "Version": "0.4.5"
    },
    "ModelVarianceExplained": 0.0690695637,
    "MotionNoise": true,
    "TotalVarianceExplained": 0.0487266811
  },
  "aroma_motion_20": {
    "CSFFraction": 0.06,
    "EdgeFraction": 0.56,
    "HighFrequencyContent": 0.17,
    "MaximumRpCorrelation": 0.55,
    "Method": {
      "Name": "ICA-AROMA",
      "Version": "0.4.5"
    },
    "ModelVarianceExplained": 0.0319875885,
    "MotionNoise": false,
    "TotalVarianceExplained": 0.0225663656
  },
  "aroma_motion_21": {
    "CSFFraction": 0.06,
    "EdgeFraction": 0.42,
    "HighFrequencyContent": 0.22,
    "MaximumRpCorrelation": 0.35,
    "Method": {
      "Name": "ICA-AROMA",
      "Version": "0.4.5"
    },
    "ModelVarianceExplained": 0.0314530495,
    "MotionNoise": false,
    "TotalVarianceExplained": 0.022189263
  },
  "aroma_motion_22": {
    "CSFFraction": 0.02,
    "EdgeFraction": 0.54,
    "HighFrequencyContent": 0.16,
    "MaximumRpCorrelation": 0.32,
    "Method": {
      "Name": "ICA-AROMA",
      "Version": "0.4.5"
    },
    "ModelVarianceExplained": 0.0303915684,
    "MotionNoise": false,
    "TotalVarianceExplained": 0.0214404172
  },
  "aroma_motion_23": {
    "CSFFraction": 0.02,
    "EdgeFraction": 0.42,
    "HighFrequencyContent": 0.11,
    "MaximumRpCorrelation": 0.5,
    "Method": {
      "Name": "ICA-AROMA",
      "Version": "0.4.5"
    },
    "ModelVarianceExplained": 0.0288913252,
    "MotionNoise": false,
    "TotalVarianceExplained": 0.0203820368
  },
  "aroma_motion_24": {
    "CSFFraction": 0.01,
    "EdgeFraction": 0.39,
    "HighFrequencyContent": 0.2,
    "MaximumRpCorrelation": 0.4,
    "Method": {
      "Name": "ICA-AROMA",
      "Version": "0.4.5"
    },
    "ModelVarianceExplained": 0.0278286171,
    "MotionNoise": false,
    "TotalVarianceExplained": 0.0196323254
  },
  "aroma_motion_3": {
    "CSFFraction": 0.02,
    "EdgeFraction": 0.55,
    "HighFrequencyContent": 0.63,
    "MaximumRpCorrelation": 0.75,
    "Method": {
      "Name": "ICA-AROMA",
      "Version": "0.4.5"
    },
    "ModelVarianceExplained": 0.0623675885,
    "MotionNoise": true,
    "TotalVarianceExplained": 0.0439986216
  },
  "aroma_motion_4": {
    "CSFFraction": 0.02,
    "EdgeFraction": 0.7,
    "HighFrequencyContent": 0.6,
    "MaximumRpCorrelation": 0.81,
    "Method": {
      "Name": "ICA-AROMA",
      "Version": "0.4.5"
    },
    "ModelVarianceExplained": 0.0604731556,
    "MotionNoise": true,
    "TotalVarianceExplained": 0.0426621511
  },
  "aroma_motion_5": {
    "CSFFraction": 0.3,
    "EdgeFraction": 0.65,
    "HighFrequencyContent": 0.14,
    "MaximumRpCorrelation": 0.21,
    "Method": {
      "Name": "ICA-AROMA",
      "Version": "0.4.5"
    },
    "ModelVarianceExplained": 0.0510146869,
    "MotionNoise": true,
    "TotalVarianceExplained": 0.0359894612
  },
  "aroma_motion_6": {
    "CSFFraction": 0.02,
    "EdgeFraction": 0.43,
    "HighFrequencyContent": 0.34,
    "MaximumRpCorrelation": 0.3,
    "Method": {
      "Name": "ICA-AROMA",
      "Version": "0.4.5"
    },
    "ModelVarianceExplained": 0.0427717903,
    "MotionNoise": false,
    "TotalVarianceExplained": 0.0301743239
  },
  "aroma_motion_7": {
    "CSFFraction": 0.01,
    "EdgeFraction": 0.27,
    "HighFrequencyContent": 0.34,
    "MaximumRpCorrelation": 0.37,
    "Method": {
      "Name": "ICA-AROMA",
      "Version": "0.4.5"
    },
    "ModelVarianceExplained": 0.0426676404,
    "MotionNoise": false,
    "TotalVarianceExplained": 0.030100849
  },
  "aroma_motion_8": {
    "CSFFraction": 0.17,
    "EdgeFraction": 0.6,
    "HighFrequencyContent": 0.17,
    "MaximumRpCorrelation": 0.32,
    "Method": {
      "Name": "ICA-AROMA",
      "Version": "0.4.5"
    },
    "ModelVarianceExplained": 0.0417066298,
    "MotionNoise": true,
    "TotalVarianceExplained": 0.0294228824
  },
  "aroma_motion_9": {
    "CSFFraction": 0.09,
    "EdgeFraction": 0.62,
    "HighFrequencyContent": 0.13,
    "MaximumRpCorrelation": 0.36,
    "Method": {
      "Name": "ICA-AROMA",
      "Version": "0.4.5"
    },
    "ModelVarianceExplained": 0.0404360328,
    "MotionNoise": false,
    "TotalVarianceExplained": 0.0285265111
  },
  "c_comp_cor_00": {
    "CumulativeVarianceExplained": 0.1576133855,
    "Mask": "CSF",
    "Method": "aCompCor",
    "Retained": true,
    "SingularValue": 98.3941167018,
    "VarianceExplained": 0.1576133855
  },
  "c_comp_cor_01": {
    "CumulativeVarianceExplained": 0.2500180578,
    "Mask": "CSF",
    "Method": "aCompCor",
    "Retained": true,
    "SingularValue": 75.3389474377,
    "VarianceExplained": 0.0924046724
  },
  "c_comp_cor_02": {
    "CumulativeVarianceExplained": 0.310646626,
    "Mask": "CSF",
    "Method": "aCompCor",
    "Retained": true,
    "SingularValue": 61.025484825,
    "VarianceExplained": 0.0606285681
  },
  "c_comp_cor_03": {
    "CumulativeVarianceExplained": 0.3509057274,
    "Mask": "CSF",
    "Method": "aCompCor",
    "Retained": true,
    "SingularValue": 49.7284154444,
    "VarianceExplained": 0.0402591014
  },
  "c_comp_cor_04": {
    "CumulativeVarianceExplained": 0.390714138,
    "Mask": "CSF",
    "Method": "aCompCor",
    "Retained": true,
    "SingularValue": 49.4492833236,
    "VarianceExplained": 0.0398084106
  },
  "c_comp_cor_05": {
    "CumulativeVarianceExplained": 0.4182931171,
    "Mask": "CSF",
    "Method": "aCompCor",
    "Retained": true,
    "SingularValue": 41.1587025059,
    "VarianceExplained": 0.0275789791
  },
  "c_comp_cor_06": {
    "CumulativeVarianceExplained": 0.4392765916,
    "Mask": "CSF",
    "Method": "aCompCor",
    "Retained": true,
    "SingularValue": 35.9013916599,
    "VarianceExplained": 0.0209834745
  },
  "c_comp_cor_07": {
    "CumulativeVarianceExplained": 0.45973872,
    "Mask": "CSF",
    "Method": "aCompCor",
    "Retained": true,
    "SingularValue": 35.4525914325,
    "VarianceExplained": 0.0204621284
  },
  "c_comp_cor_08": {
    "CumulativeVarianceExplained": 0.4759830976,
    "Mask": "CSF",
    "Method": "aCompCor",
    "Retained": true,
    "SingularValue": 31.5881448027,
    "VarianceExplained": 0.0162443776
  },
  "c_comp_cor_09": {
    "CumulativeVarianceExplained": 0.4908635918,
    "Mask": "CSF",
    "Method": "aCompCor",
    "Retained": true,
    "SingularValue": 30.2330010495,
    "VarianceExplained": 0.0148804941
  },
  "c_comp_cor_10": {
    "CumulativeVarianceExplained": 0.5055383401,
    "Mask": "CSF",
    "Method": "aCompCor",
    "Retained": true,
    "SingularValue": 30.0232646224,
    "VarianceExplained": 0.0146747484
  },
  "dropped_0": {
    "CumulativeVarianceExplained": 0.4055819656,
    "Mask": "Edge",
    "Method": "EdgeRegressor",
    "Retained": false,
    "SingularValue": 119.005618057,
    "VarianceExplained": 0.0078107513
  },
  "dropped_1": {
    "CumulativeVarianceExplained": 0.4133236834,
    "Mask": "Edge",
    "Method": "EdgeRegressor",
    "Retained": false,
    "SingularValue": 118.4785490811,
    "VarianceExplained": 0.0077417178
  },
  "dropped_10": {
    "CumulativeVarianceExplained": 0.4793210547,
    "Mask": "Edge",
    "Method": "EdgeRegressor",
    "Retained": false,
    "SingularValue": 112.8347401881,
    "VarianceExplained": 0.0070217207
  },
  "dropped_100": {
    "CumulativeVarianceExplained": 0.9757750112,
    "Mask": "Edge",
    "Method": "EdgeRegressor",
    "Retained": false,
    "SingularValue": 89.1539542069,
    "VarianceExplained": 0.0043836826
  },
  "dropped_101": {
    "CumulativeVarianceExplained": 0.9801365677,
    "Mask": "Edge",
    "Method": "EdgeRegressor",
    "Retained": false,
    "SingularValue": 88.9286720537,
    "VarianceExplained": 0.0043615564
  },
  "dropped_102": {
    "CumulativeVarianceExplained": 0.9844661601,
    "Mask": "Edge",
    "Method": "EdgeRegressor",
    "Retained": false,
    "SingularValue": 88.6022121676,
    "VarianceExplained": 0.0043295924
  },
  "dropped_103": {
    "CumulativeVarianceExplained": 0.9887282058,
    "Mask": "Edge",
    "Method": "EdgeRegressor",
    "Retained": false,
    "SingularValue": 87.9083469277,
    "VarianceExplained": 0.0042620458
  },
  "dropped_104": {
    "CumulativeVarianceExplained": 0.9929324139,
    "Mask": "Edge",
    "Method": "EdgeRegressor",
    "Retained": false,
    "SingularValue": 87.3098329417,
    "VarianceExplained": 0.004204208
  },
  "dropped_105": {
    "CumulativeVarianceExplained": 0.9969455635,
    "Mask": "Edge",
    "Method": "EdgeRegressor",
    "Retained": false,
    "SingularValue": 85.3028877614,
    "VarianceExplained": 0.0040131496
  },
  "dropped_106": {
    "CumulativeVarianceExplained": 1.0,
    "Mask": "Edge",
    "Method": "EdgeRegressor",
    "Retained": false,
    "SingularValue": 74.4194765313,
    "VarianceExplained": 0.0030544365
  },
  "dropped_107": {
    "CumulativeVarianceExplained": 1.0,
    "Mask": "Edge",
    "Method": "EdgeRegressor",
    "Retained": false,
    "SingularValue": 0.0,
    "VarianceExplained": 0.0
  },
  "dropped_108": {
    "CumulativeVarianceExplained": 1.0,
    "Mask": "Edge",
    "Method": "EdgeRegressor",
    "Retained": false,
    "SingularValue": 0.0,
    "VarianceExplained": 0.0
  },
  "dropped_109": {
    "CumulativeVarianceExplained": 1.0,
    "Mask": "Edge",
    "Method": "EdgeRegressor",
    "Retained": false,
    "SingularValue": 0.0,
    "VarianceExplained": 0.0
  },
  "dropped_11": {
    "CumulativeVarianceExplained": 0.4863011574,
    "Mask": "Edge",
    "Method": "EdgeRegressor",
    "Retained": false,
    "SingularValue": 112.4998551368,
    "VarianceExplained": 0.0069801026
  },
  "dropped_110": {
    "CumulativeVarianceExplained": 1.0,
    "Mask": "Edge",
    "Method": "EdgeRegressor",
    "Retained": false,
    "SingularValue": 0.0,
    "VarianceExplained": 0.0
  },
  "dropped_12": {
    "CumulativeVarianceExplained": 0.4932583808,
    "Mask": "Edge",
    "Method": "EdgeRegressor",
    "Retained": false,
    "SingularValue": 112.315329194,
    "VarianceExplained": 0.0069572234
  },
  "dropped_13": {
    "CumulativeVarianceExplained": 0.5001375107,
    "Mask": "Edge",
    "Method": "EdgeRegressor",
    "Retained": false,
    "SingularValue": 111.6831906938,
    "VarianceExplained": 0.0068791299
  },
  "dropped_14": {
    "CumulativeVarianceExplained": 0.506978,
    "Mask": "Edge",
    "Method": "EdgeRegressor",
    "Retained": false,
    "SingularValue": 111.3690828384,
    "VarianceExplained": 0.0068404893
  },
  "dropped_15": {
    "CumulativeVarianceExplained": 0.5137544631,
    "Mask": "Edge",
    "Method": "EdgeRegressor",
    "Retained": false,
    "SingularValue": 110.8466564427,
    "VarianceExplained": 0.0067764631
  },
  "dropped_16": {
    "CumulativeVarianceExplained": 0.520467926,
    "Mask": "Edge",
    "Method": "EdgeRegressor",
    "Retained": false,
    "SingularValue": 110.3301871708,
    "VarianceExplained": 0.0067134629
  },
  "dropped_17": {
    "CumulativeVarianceExplained": 0.5271237298,
    "Mask": "Edge",
    "Method": "EdgeRegressor",
    "Retained": false,
    "SingularValue": 109.8553757414,
    "VarianceExplained": 0.0066558038
  },
  "dropped_18": {
    "CumulativeVarianceExplained": 0.5337099219,
    "Mask": "Edge",
    "Method": "EdgeRegressor",
    "Retained": false,
    "SingularValue": 109.2793885915,
    "VarianceExplained": 0.0065861921
  },
  "dropped_19": {
    "CumulativeVarianceExplained": 0.5402412167,
    "Mask": "Edge",
    "Method": "EdgeRegressor",
    "Retained": false,
    "SingularValue": 108.82300202,
    "VarianceExplained": 0.0065312948
  },
  "dropped_2": {
    "CumulativeVarianceExplained": 0.4209232538,
    "Mask": "Edge",
    "Method": "EdgeRegressor",
    "Retained": false,
    "SingularValue": 117.3858047937,
    "VarianceExplained": 0.0075995705
  },
  "dropped_20": {
    "CumulativeVarianceExplained": 0.5467485448,
    "Mask": "Edge",
    "Method": "EdgeRegressor",
    "Retained": false,
    "SingularValue": 108.623154398,
    "VarianceExplained": 0.0065073281
  },
  "dropped_21": {
    "CumulativeVarianceExplained": 0.5532122752,
    "Mask": "Edge",
    "Method": "EdgeRegressor",
    "Retained": false,
    "SingularValue": 108.2586673665,
    "VarianceExplained": 0.0064637304
  },
  "dropped_22": {
    "CumulativeVarianceExplained": 0.5596501807,
    "Mask": "Edge",
    "Method": "EdgeRegressor",
    "Retained": false,
    "SingularValue": 108.042184548,
    "VarianceExplained": 0.0064379055
  },
  "dropped_23": {
    "CumulativeVarianceExplained": 0.5660275673,
    "Mask": "Edge",
    "Method": "EdgeRegressor",
    "Retained": false,
    "SingularValue": 107.53316567,
    "VarianceExplained": 0.0063773866
  },
  "dropped_24": {
    "CumulativeVarianceExplained": 0.5723768946,
    "Mask": "Edge",
    "Method": "EdgeRegressor",
    "Retained": false,
    "SingularValue": 107.2963420299,
    "VarianceExplained": 0.0063493273
  },
  "dropped_25": {
    "CumulativeVarianceExplained": 0.5786976236,
    "Mask": "Edge",
    "Method": "EdgeRegressor",
    "Retained": false,
    "SingularValue": 107.0544306643,
    "VarianceExplained": 0.0063207291
  },
  "dropped_26": {
    "CumulativeVarianceExplained": 0.5849754816,
    "Mask": "Edge",
    "Method": "EdgeRegressor",
    "Retained": false,
    "SingularValue": 106.6907585612,
    "VarianceExplained": 0.006277858
  },
  "dropped_27": {
    "CumulativeVarianceExplained": 0.5912045022,
    "Mask": "Edge",
    "Method": "EdgeRegressor",
    "Retained": false,
    "SingularValue": 106.2749580827,
    "VarianceExplained": 0.0062290206
  },
  "dropped_28": {
    "CumulativeVarianceExplained": 0.597399126,
    "Mask": "Edge",
    "Method": "EdgeRegressor",
    "Retained": false,
    "SingularValue": 105.9811253568,
    "VarianceExplained": 0.0061946238
  },
  "dropped_29": {
    "CumulativeVarianceExplained": 0.6035692489,
    "Mask": "Edge",
    "Method": "EdgeRegressor",
    "Retained": false,
    "SingularValue": 105.7713297653,
    "VarianceExplained": 0.0061701229
  },
  "dropped_3": {
    "CumulativeVarianceExplained": 0.428448281,
    "Mask": "Edge",
    "Method": "EdgeRegressor",
    "Retained": false,
    "SingularValue": 116.8086741703,
    "VarianceExplained": 0.0075250272
  },
  "dropped_30": {
    "CumulativeVarianceExplained": 0.6097223638,
    "Mask": "Edge",
    "Method": "EdgeRegressor",
    "Retained": false,
    "SingularValue": 105.625449675,
    "VarianceExplained": 0.0061531149
  },
  "dropped_31": {
    "CumulativeVarianceExplained": 0.6158512101,
    "Mask": "Edge",
    "Method": "EdgeRegressor",
    "Retained": false,
    "SingularValue": 105.4169451715,
    "VarianceExplained": 0.0061288464
  },
  "dropped_32": {
    "CumulativeVarianceExplained": 0.6219250586,
    "Mask": "Edge",
    "Method": "EdgeRegressor",
    "Retained": false,
    "SingularValue": 104.9428935837,
    "VarianceExplained": 0.0060738485
  },
  "dropped_33": {
    "CumulativeVarianceExplained": 0.6279832845,
    "Mask": "Edge",
    "Method": "EdgeRegressor",
    "Retained": false,
    "SingularValue": 104.8078444432,
    "VarianceExplained": 0.0060582259
  },
  "dropped_34": {
    "CumulativeVarianceExplained": 0.634005527,
    "Mask": "Edge",
    "Method": "EdgeRegressor",
    "Retained": false,
    "SingularValue": 104.496123506,
    "VarianceExplained": 0.0060222425
  },
  "dropped_35": {
    "CumulativeVarianceExplained": 0.6400003402,
    "Mask": "Edge",
    "Method": "EdgeRegressor",
    "Retained": false,
    "SingularValue": 104.2578788801,
    "VarianceExplained": 0.0059948132
  },
  "dropped_36": {
    "CumulativeVarianceExplained": 0.6459638241,
    "Mask": "Edge",
    "Method": "EdgeRegressor",
    "Retained": false,
    "SingularValue": 103.9850931356,
    "VarianceExplained": 0.0059634839
  },
  "dropped_37": {
    "CumulativeVarianceExplained": 0.6518740999,
    "Mask": "Edge",
    "Method": "EdgeRegressor",
    "Retained": false,
    "SingularValue": 103.5201600133,
    "VarianceExplained": 0.0059102759
  },
  "dropped_38": {
    "CumulativeVarianceExplained": 0.6577757774,
    "Mask": "Edge",
    "Method": "EdgeRegressor",
    "Retained": false,
    "SingularValue": 103.4448308733,
    "VarianceExplained": 0.0059016775
  },
  "dropped_39": {
    "CumulativeVarianceExplained": 0.663618316,
    "Mask": "Edge",
    "Method": "EdgeRegressor",
    "Retained": false,
    "SingularValue": 102.9252315795,
    "VarianceExplained": 0.0058425386
  },
  "dropped_4": {
    "CumulativeVarianceExplained": 0.4359651802,
    "Mask": "Edge",
    "Method": "EdgeRegressor",
    "Retained": false,
    "SingularValue": 116.7455737387,
    "VarianceExplained": 0.0075168993
  },
  "dropped_40": {
    "CumulativeVarianceExplained": 0.6694406839,
    "Mask": "Edge",
    "Method": "EdgeRegressor",
    "Retained": false,
    "SingularValue": 102.7474097453,
    "VarianceExplained": 0.0058223679
  },
  "dropped_41": {
    "CumulativeVarianceExplained": 0.6752203527,
    "Mask": "Edge",
    "Method": "EdgeRegressor",
    "Retained": false,
    "SingularValue": 102.3699603201,
    "VarianceExplained": 0.0057796688
  },
  "dropped_42": {
    "CumulativeVarianceExplained": 0.6809939904,
    "Mask": "Edge",
    "Method": "EdgeRegressor",
    "Retained": false,
    "SingularValue": 102.3165347616,
    "VarianceExplained": 0.0057736377
  },
  "dropped_43": {
    "CumulativeVarianceExplained": 0.6867582695,
    "Mask": "Edge",
    "Method": "EdgeRegressor",
    "Retained": false,
    "SingularValue": 102.2335780145,
    "VarianceExplained": 0.0057642791
  },
  "dropped_44": {
    "CumulativeVarianceExplained": 0.6925022154,
    "Mask": "Edge",
    "Method": "EdgeRegressor",
    "Retained": false,
    "SingularValue": 102.0531056824,
    "VarianceExplained": 0.0057439458
  },
  "dropped_45": {
    "CumulativeVarianceExplained": 0.6982069567,
    "Mask": "Edge",
    "Method": "EdgeRegressor",
    "Retained": false,
    "SingularValue": 101.7042351189,
    "VarianceExplained": 0.0057047413
  },
  "dropped_46": {
    "CumulativeVarianceExplained": 0.7038989632,
    "Mask": "Edge",
    "Method": "EdgeRegressor",
    "Retained": false,
    "SingularValue": 101.5906528619,
    "VarianceExplained": 0.0056920065
  },
  "dropped_47": {
    "CumulativeVarianceExplained": 0.7095724163,
    "Mask": "Edge",
    "Method": "EdgeRegressor",
    "Retained": false,
    "SingularValue": 101.4249485603,
    "VarianceExplained": 0.0056734532
  },
  "dropped_48": {
    "CumulativeVarianceExplained": 0.7152095671,
    "Mask": "Edge",
    "Method": "EdgeRegressor",
    "Retained": false,
    "SingularValue": 101.0999362766,
    "VarianceExplained": 0.0056371507
  },
  "dropped_49": {
    "CumulativeVarianceExplained": 0.720798852,
    "Mask": "Edge",
    "Method": "EdgeRegressor",
    "Retained": false,
    "SingularValue": 100.6697949605,
    "VarianceExplained": 0.0055892849
  },
  "dropped_5": {
    "CumulativeVarianceExplained": 0.4434194423,
    "Mask": "Edge",
    "Method": "EdgeRegressor",
    "Retained": false,
    "SingularValue": 116.2581444019,
    "VarianceExplained": 0.0074542621
  },
  "dropped_50": {
    "CumulativeVarianceExplained": 0.7263619929,
    "Mask": "Edge",
    "Method": "EdgeRegressor",
    "Retained": false,
    "SingularValue": 100.4340764854,
    "VarianceExplained": 0.0055631409
  },
  "dropped_51": {
    "CumulativeVarianceExplained": 0.7319192273,
    "Mask": "Edge",
    "Method": "EdgeRegressor",
    "Retained": false,
    "SingularValue": 100.3807451213,
    "VarianceExplained": 0.0055572344
  },
  "dropped_52": {
    "CumulativeVarianceExplained": 0.7374592766,
    "Mask": "Edge",
    "Method": "EdgeRegressor",
    "Retained": false,
    "SingularValue": 100.2254170125,
    "VarianceExplained": 0.0055400493
  },
  "dropped_53": {
    "CumulativeVarianceExplained": 0.7429762015,
    "Mask": "Edge",
    "Method": "EdgeRegressor",
    "Retained": false,
    "SingularValue": 100.0160260418,
    "VarianceExplained": 0.0055169249
  },
  "dropped_54": {
    "CumulativeVarianceExplained": 0.7484545179,
    "Mask": "Edge",
    "Method": "EdgeRegressor",
    "Retained": false,
    "SingularValue": 99.6654459116,
    "VarianceExplained": 0.0054783164
  },
  "dropped_55": {
    "CumulativeVarianceExplained": 0.7539274833,
    "Mask": "Edge",
    "Method": "EdgeRegressor",
    "Retained": false,
    "SingularValue": 99.6167602148,
    "VarianceExplained": 0.0054729655
  },
  "dropped_56": {
    "CumulativeVarianceExplained": 0.7593707218,
    "Mask": "Edge",
    "Method": "EdgeRegressor",
    "Retained": false,
    "SingularValue": 99.3458521876,
    "VarianceExplained": 0.0054432385
  },
  "dropped_57": {
    "CumulativeVarianceExplained": 0.7647854968,
    "Mask": "Edge",
    "Method": "EdgeRegressor",
    "Retained": false,
    "SingularValue": 99.0857647547,
    "VarianceExplained": 0.005414775
  },
  "dropped_58": {
    "CumulativeVarianceExplained": 0.7701786923,
    "Mask": "Edge",
    "Method": "EdgeRegressor",
    "Retained": false,
    "SingularValue": 98.888124966,
    "VarianceExplained": 0.0053931955
  },
  "dropped_59": {
    "CumulativeVarianceExplained": 0.7755488917,
    "Mask": "Edge",
    "Method": "EdgeRegressor",
    "Retained": false,
    "SingularValue": 98.6770738733,
    "VarianceExplained": 0.0053701993
  },
  "dropped_6": {
    "CumulativeVarianceExplained": 0.4507226482,
    "Mask": "Edge",
    "Method": "EdgeRegressor",
    "Retained": false,
    "SingularValue": 115.0741650467,
    "VarianceExplained": 0.0073032059
  },
  "dropped_60": {
    "CumulativeVarianceExplained": 0.7808931552,
    "Mask": "Edge",
    "Method": "EdgeRegressor",
    "Retained": false,
    "SingularValue": 98.4385012128,
    "VarianceExplained": 0.0053442636
  },
  "dropped_61": {
    "CumulativeVarianceExplained": 0.7862139754,
    "Mask": "Edge",
    "Method": "EdgeRegressor",
    "Retained": false,
    "SingularValue": 98.2223559581,
    "VarianceExplained": 0.0053208201
  },
  "dropped_62": {
    "CumulativeVarianceExplained": 0.7914784468,
    "Mask": "Edge",
    "Method": "EdgeRegressor",
    "Retained": false,
    "SingularValue": 97.7008733068,
    "VarianceExplained": 0.0052644714
  },
  "dropped_63": {
    "CumulativeVarianceExplained": 0.7967203387,
    "Mask": "Edge",
    "Method": "EdgeRegressor",
    "Retained": false,
    "SingularValue": 97.4911270237,
    "VarianceExplained": 0.0052418919
  },
  "dropped_64": {
    "CumulativeVarianceExplained": 0.8019432521,
    "Mask": "Edge",
    "Method": "EdgeRegressor",
    "Retained": false,
    "SingularValue": 97.31448031,
    "VarianceExplained": 0.0052229133
  },
  "dropped_65": {
    "CumulativeVarianceExplained": 0.8071591363,
    "Mask": "Edge",
    "Method": "EdgeRegressor",
    "Retained": false,
    "SingularValue": 97.2489751201,
    "VarianceExplained": 0.0052158843
  },
  "dropped_66": {
    "CumulativeVarianceExplained": 0.8123491583,
    "Mask": "Edge",
    "Method": "EdgeRegressor",
    "Retained": false,
    "SingularValue": 97.0075768247,
    "VarianceExplained": 0.005190022
  },
  "dropped_67": {
    "CumulativeVarianceExplained": 0.8175247131,
    "Mask": "Edge",
    "Method": "EdgeRegressor",
    "Retained": false,
    "SingularValue": 96.8722781129,
    "VarianceExplained": 0.0051755548
  },
  "dropped_68": {
    "CumulativeVarianceExplained": 0.8226497927,
    "Mask": "Edge",
    "Method": "EdgeRegressor",
    "Retained": false,
    "SingularValue": 96.3987425691,
    "VarianceExplained": 0.0051250797
  },
  "dropped_69": {
    "CumulativeVarianceExplained": 0.8277658324,
    "Mask": "Edge",
    "Method": "EdgeRegressor",
    "Retained": false,
    "SingularValue": 96.3136871561,
    "VarianceExplained": 0.0051160396
  },
  "dropped_7": {
    "CumulativeVarianceExplained": 0.458014564,
    "Mask": "Edge",
    "Method": "EdgeRegressor",
    "Retained": false,
    "SingularValue": 114.9851826411,
    "VarianceExplained": 0.0072919157
  },
  "dropped_70": {
    "CumulativeVarianceExplained": 0.8328617479,
    "Mask": "Edge",
    "Method": "EdgeRegressor",
    "Retained": false,
    "SingularValue": 96.1240736157,
    "VarianceExplained": 0.0050959155
  },
  "dropped_71": {
    "CumulativeVarianceExplained": 0.8379314767,
    "Mask": "Edge",
    "Method": "EdgeRegressor",
    "Retained": false,
    "SingularValue": 95.8767767949,
    "VarianceExplained": 0.0050697289
  },
  "dropped_72": {
    "CumulativeVarianceExplained": 0.8429676777,
    "Mask": "Edge",
    "Method": "EdgeRegressor",
    "Retained": false,
    "SingularValue": 95.5592174039,
    "VarianceExplained": 0.005036201
  },
  "dropped_73": {
    "CumulativeVarianceExplained": 0.8479764821,
    "Mask": "Edge",
    "Method": "EdgeRegressor",
    "Retained": false,
    "SingularValue": 95.2989453041,
    "VarianceExplained": 0.0050088044
  },
  "dropped_74": {
    "CumulativeVarianceExplained": 0.8529809214,
    "Mask": "Edge",
    "Method": "EdgeRegressor",
    "Retained": false,
    "SingularValue": 95.2574110791,
    "VarianceExplained": 0.0050044394
  },
  "dropped_75": {
    "CumulativeVarianceExplained": 0.8579591895,
    "Mask": "Edge",
    "Method": "EdgeRegressor",
    "Retained": false,
    "SingularValue": 95.0080048181,
    "VarianceExplained": 0.0049782681
  },
  "dropped_76": {
    "CumulativeVarianceExplained": 0.8629340621,
    "Mask": "Edge",
    "Method": "EdgeRegressor",
    "Retained": false,
    "SingularValue": 94.9755992974,
    "VarianceExplained": 0.0049748726
  },
  "dropped_77": {
    "CumulativeVarianceExplained": 0.8678888792,
    "Mask": "Edge",
    "Method": "EdgeRegressor",
    "Retained": false,
    "SingularValue": 94.7839650852,
    "VarianceExplained": 0.0049548171
  },
  "dropped_78": {
    "CumulativeVarianceExplained": 0.8728209634,
    "Mask": "Edge",
    "Method": "EdgeRegressor",
    "Retained": false,
    "SingularValue": 94.5662789158,
    "VarianceExplained": 0.0049320842
  },
  "dropped_79": {
    "CumulativeVarianceExplained": 0.8777346979,
    "Mask": "Edge",
    "Method": "EdgeRegressor",
    "Retained": false,
    "SingularValue": 94.3901991179,
    "VarianceExplained": 0.0049137345
  },
  "dropped_8": {
    "CumulativeVarianceExplained": 0.4652413983,
    "Mask": "Edge",
    "Method": "EdgeRegressor",
    "Retained": false,
    "SingularValue": 114.4709029276,
    "VarianceExplained": 0.0072268343
  },
  "dropped_80": {
    "CumulativeVarianceExplained": 0.882629466,
    "Mask": "Edge",
    "Method": "EdgeRegressor",
    "Retained": false,
    "SingularValue": 94.2078558134,
    "VarianceExplained": 0.0048947681
  },
  "dropped_81": {
    "CumulativeVarianceExplained": 0.8875057799,
    "Mask": "Edge",
    "Method": "EdgeRegressor",
    "Retained": false,
    "SingularValue": 94.030096647,
    "VarianceExplained": 0.0048763138
  },
  "dropped_82": {
    "CumulativeVarianceExplained": 0.8923527906,
    "Mask": "Edge",
    "Method": "EdgeRegressor",
    "Retained": false,
    "SingularValue": 93.7471447275,
    "VarianceExplained": 0.0048470107
  },
  "dropped_83": {
    "CumulativeVarianceExplained": 0.8971743522,
    "Mask": "Edge",
    "Method": "EdgeRegressor",
    "Retained": false,
    "SingularValue": 93.5007121928,
    "VarianceExplained": 0.0048215616
  },
  "dropped_84": {
    "CumulativeVarianceExplained": 0.9019849541,
    "Mask": "Edge",
    "Method": "EdgeRegressor",
    "Retained": false,
    "SingularValue": 93.3943850073,
    "VarianceExplained": 0.0048106019
  },
  "dropped_85": {
    "CumulativeVarianceExplained": 0.9067825319,
    "Mask": "Edge",
    "Method": "EdgeRegressor",
    "Retained": false,
    "SingularValue": 93.2678730788,
    "VarianceExplained": 0.0047975778
  },
  "dropped_86": {
    "CumulativeVarianceExplained": 0.9115412402,
    "Mask": "Edge",
    "Method": "EdgeRegressor",
    "Retained": false,
    "SingularValue": 92.8892809263,
    "VarianceExplained": 0.0047587083
  },
  "dropped_87": {
    "CumulativeVarianceExplained": 0.9162831509,
    "Mask": "Edge",
    "Method": "EdgeRegressor",
    "Retained": false,
    "SingularValue": 92.7251923688,
    "VarianceExplained": 0.0047419107
  },
  "dropped_88": {
    "CumulativeVarianceExplained": 0.9210074011,
    "Mask": "Edge",
    "Method": "EdgeRegressor",
    "Retained": false,
    "SingularValue": 92.5523619586,
    "VarianceExplained": 0.0047242503
  },
  "dropped_89": {
    "CumulativeVarianceExplained": 0.9257258971,
    "Mask": "Edge",
    "Method": "EdgeRegressor",
    "Retained": false,
    "SingularValue": 92.4959793549,
    "VarianceExplained": 0.004718496
  },
  "dropped_9": {
    "CumulativeVarianceExplained": 0.4722993341,
    "Mask": "Edge",
    "Method": "EdgeRegressor",
    "Retained": false,
    "SingularValue": 113.1253431727,
    "VarianceExplained": 0.0070579358
  },
  "dropped_90": {
    "CumulativeVarianceExplained": 0.9304319271,
    "Mask": "Edge",
    "Method": "EdgeRegressor",
    "Retained": false,
    "SingularValue": 92.3737137679,
    "VarianceExplained": 0.00470603
  },
  "dropped_91": {
    "CumulativeVarianceExplained": 0.9350868937,
    "Mask": "Edge",
    "Method": "EdgeRegressor",
    "Retained": false,
    "SingularValue": 91.87119019,
    "VarianceExplained": 0.0046549666
  },
  "dropped_92": {
    "CumulativeVarianceExplained": 0.9397233807,
    "Mask": "Edge",
    "Method": "EdgeRegressor",
    "Retained": false,
    "SingularValue": 91.6886508547,
    "VarianceExplained": 0.004636487
  },
  "dropped_93": {
    "CumulativeVarianceExplained": 0.9443380095,
    "Mask": "Edge",
    "Method": "EdgeRegressor",
    "Retained": false,
    "SingularValue": 91.4722670881,
    "VarianceExplained": 0.0046146288
  },
  "dropped_94": {
    "CumulativeVarianceExplained": 0.9489214883,
    "Mask": "Edge",
    "Method": "EdgeRegressor",
    "Retained": false,
    "SingularValue": 91.1630132346,
    "VarianceExplained": 0.0045834788
  },
  "dropped_95": {
    "CumulativeVarianceExplained": 0.953470282,
    "Mask": "Edge",
    "Method": "EdgeRegressor",
    "Retained": false,
    "SingularValue": 90.8174245992,
    "VarianceExplained": 0.0045487938
  },
  "dropped_96": {
    "CumulativeVarianceExplained": 0.9579704907,
    "Mask": "Edge",
    "Method": "EdgeRegressor",
    "Retained": false,
    "SingularValue": 90.3311175465,
    "VarianceExplained": 0.0045002086
  },
  "dropped_97": {
    "CumulativeVarianceExplained": 0.9624670992,
    "Mask": "Edge",
    "Method": "EdgeRegressor",
    "Retained": false,
    "SingularValue": 90.2949786521,
    "VarianceExplained": 0.0044966085
  },
  "dropped_98": {
    "CumulativeVarianceExplained": 0.9669406405,
    "Mask": "Edge",
    "Method": "EdgeRegressor",
    "Retained": false,
    "SingularValue": 90.0630777016,
    "VarianceExplained": 0.0044735413
  },
  "dropped_99": {
    "CumulativeVarianceExplained": 0.9713913286,
    "Mask": "Edge",
    "Method": "EdgeRegressor",
    "Retained": false,
    "SingularValue": 89.8327388421,
    "VarianceExplained": 0.0044506881
  },
  "edge_comp_00": {
    "CumulativeVarianceExplained": 0.0673710422,
    "Mask": "Edge",
    "Method": "EdgeRegressor",
    "Retained": true,
    "SingularValue": 349.5084593567,
    "VarianceExplained": 0.0673710422
  },
  "edge_comp_01": {
    "CumulativeVarianceExplained": 0.121075851,
    "Mask": "Edge",
    "Method": "EdgeRegressor",
    "Retained": true,
    "SingularValue": 312.0524854681,
    "VarianceExplained": 0.0537048088
  },
  "edge_comp_02": {
    "CumulativeVarianceExplained": 0.1568581224,
    "Mask": "Edge",
    "Method": "EdgeRegressor",
    "Retained": true,
    "SingularValue": 254.7152878743,
    "VarianceExplained": 0.0357822715
  },
  "edge_comp_03": {
    "CumulativeVarianceExplained": 0.1830787439,
    "Mask": "Edge",
    "Method": "EdgeRegressor",
    "Retained": true,
    "SingularValue": 218.0432009998,
    "VarianceExplained": 0.0262206214
  },
  "edge_comp_04": {
    "CumulativeVarianceExplained": 0.2051312856,
    "Mask": "Edge",
    "Method": "EdgeRegressor",
    "Retained": true,
    "SingularValue": 199.9633412406,
    "VarianceExplained": 0.0220525417
  },
  "edge_comp_05": {
    "CumulativeVarianceExplained": 0.2209361864,
    "Mask": "Edge",
    "Method": "EdgeRegressor",
    "Retained": true,
    "SingularValue": 169.2844031806,
    "VarianceExplained": 0.0158049009
  },
  "edge_comp_06": {
    "CumulativeVarianceExplained": 0.233995097,
    "Mask": "Edge",
    "Method": "EdgeRegressor",
    "Retained": true,
    "SingularValue": 153.8772909629,
    "VarianceExplained": 0.0130589105
  },
  "edge_comp_07": {
    "CumulativeVarianceExplained": 0.2463020994,
    "Mask": "Edge",
    "Method": "EdgeRegressor",
    "Retained": true,
    "SingularValue": 149.3816326807,
    "VarianceExplained": 0.0123070024
  },
  "edge_comp_08": {
    "CumulativeVarianceExplained": 0.2582178701,
    "Mask": "Edge",
    "Method": "EdgeRegressor",
    "Retained": true,
    "SingularValue": 146.9880834327,
    "VarianceExplained": 0.0119157707
  },
  "edge_comp_09": {
    "CumulativeVarianceExplained": 0.2694899304,
    "Mask": "Edge",
    "Method": "EdgeRegressor",
    "Retained": true,
    "SingularValue": 142.9626900814,
    "VarianceExplained": 0.0112720604
  },
  "edge_comp_10": {
    "CumulativeVarianceExplained": 0.2804515717,
    "Mask": "Edge",
    "Method": "EdgeRegressor",
    "Retained": true,
    "SingularValue": 140.980436973,
    "VarianceExplained": 0.0109616413
  },
  "edge_comp_11": {
    "CumulativeVarianceExplained": 0.2909714886,
    "Mask": "Edge",
    "Method": "EdgeRegressor",
    "Retained": true,
    "SingularValue": 138.1106638842,
    "VarianceExplained": 0.0105199169
  },
  "edge_comp_12": {
    "CumulativeVarianceExplained": 0.3010680749,
    "Mask": "Edge",
    "Method": "EdgeRegressor",
    "Retained": true,
    "SingularValue": 135.3032847709,
    "VarianceExplained": 0.0100965863
  },
  "edge_comp_13": {
    "CumulativeVarianceExplained": 0.3108903872,
    "Mask": "Edge",
    "Method": "EdgeRegressor",
    "Retained": true,
    "SingularValue": 133.4528726377,
    "VarianceExplained": 0.0098223122
  },
  "edge_comp_14": {
    "CumulativeVarianceExplained": 0.320682745,
    "Mask": "Edge",
    "Method": "EdgeRegressor",
    "Retained": true,
    "SingularValue": 133.2492264837,
    "VarianceExplained": 0.0097923578
  },
  "edge_comp_15": {
    "CumulativeVarianceExplained": 0.3300570314,
    "Mask": "Edge",
    "Method": "EdgeRegressor",
    "Retained": true,
    "SingularValue": 130.3737526177,
    "VarianceExplained": 0.0093742863
  },
  "edge_comp_16": {
    "CumulativeVarianceExplained": 0.339170568,
    "Mask": "Edge",
    "Method": "EdgeRegressor",
    "Retained": true,
    "SingularValue": 128.5477654919,
    "VarianceExplained": 0.0091135367
  },
  "edge_comp_17": {
    "CumulativeVarianceExplained": 0.3481415195,
    "Mask": "Edge",
    "Method": "EdgeRegressor",
    "Retained": true,
    "SingularValue": 127.5382081155,
    "VarianceExplained": 0.0089709514
  },
  "edge_comp_18": {
    "CumulativeVarianceExplained": 0.3567953119,
    "Mask": "Edge",
    "Method": "EdgeRegressor",
    "Retained": true,
    "SingularValue": 125.2634290898,
    "VarianceExplained": 0.0086537925
  },
  "edge_comp_19": {
    "CumulativeVarianceExplained": 0.3652685808,
    "Mask": "Edge",
    "Method": "EdgeRegressor",
    "Retained": true,
    "SingularValue": 123.9500063324,
    "VarianceExplained": 0.0084732689
  },
  "edge_comp_20": {
    "CumulativeVarianceExplained": 0.3735244951,
    "Mask": "Edge",
    "Method": "EdgeRegressor",
    "Retained": true,
    "SingularValue": 122.3499078228,
    "VarianceExplained": 0.0082559143
  },
  "edge_comp_21": {
    "CumulativeVarianceExplained": 0.3817177654,
    "Mask": "Edge",
    "Method": "EdgeRegressor",
    "Retained": true,
    "SingularValue": 121.8848426665,
    "VarianceExplained": 0.0081932703
  },
  "edge_comp_22": {
    "CumulativeVarianceExplained": 0.3898316862,
    "Mask": "Edge",
    "Method": "EdgeRegressor",
    "Retained": true,
    "SingularValue": 121.2931962171,
    "VarianceExplained": 0.0081139208
  },
  "edge_comp_23": {
    "CumulativeVarianceExplained": 0.3977712142,
    "Mask": "Edge",
    "Method": "EdgeRegressor",
    "Retained": true,
    "SingularValue": 119.9826368289,
    "VarianceExplained": 0.007939528
  },
  "t_comp_cor_00": {
    "CumulativeVarianceExplained": 0.263715157,
    "Method": "tCompCor",
    "Retained": true,
    "SingularValue": 189.7186421973,
    "VarianceExplained": 0.263715157
  },
  "t_comp_cor_01": {
    "CumulativeVarianceExplained": 0.3998685447,
    "Method": "tCompCor",
    "Retained": true,
    "SingularValue": 136.3190930157,
    "VarianceExplained": 0.1361533877
  },
  "t_comp_cor_02": {
    "CumulativeVarianceExplained": 0.5086275949,
    "Method": "tCompCor",
    "Retained": true,
    "SingularValue": 121.8358689617,
    "VarianceExplained": 0.1087590502
  },
  "w_comp_cor_00": {
    "CumulativeVarianceExplained": 0.0351581292,
    "Mask": "WM",
    "Method": "aCompCor",
    "Retained": true,
    "SingularValue": 94.5627758533,
    "VarianceExplained": 0.0351581292
  },
  "w_comp_cor_01": {
    "CumulativeVarianceExplained": 0.0575541406,
    "Mask": "WM",
    "Method": "aCompCor",
    "Retained": true,
    "SingularValue": 75.4731842185,
    "VarianceExplained": 0.0223960114
  },
  "w_comp_cor_02": {
    "CumulativeVarianceExplained": 0.0771521038,
    "Mask": "WM",
    "Method": "aCompCor",
    "Retained": true,
    "SingularValue": 70.6013170859,
    "VarianceExplained": 0.0195979633
  },
  "w_comp_cor_03": {
    "CumulativeVarianceExplained": 0.0941859521,
    "Mask": "WM",
    "Method": "aCompCor",
    "Retained": true,
    "SingularValue": 65.820885488,
    "VarianceExplained": 0.0170338483
  },
  "w_comp_cor_04": {
    "CumulativeVarianceExplained": 0.109924714,
    "Mask": "WM",
    "Method": "aCompCor",
    "Retained": true,
    "SingularValue": 63.2692397751,
    "VarianceExplained": 0.0157387619
  },
  "w_comp_cor_05": {
    "CumulativeVarianceExplained": 0.1252279414,
    "Mask": "WM",
    "Method": "aCompCor",
    "Retained": true,
    "SingularValue": 62.3876819719,
    "VarianceExplained": 0.0153032274
  },
  "w_comp_cor_06": {
    "CumulativeVarianceExplained": 0.1399444846,
    "Mask": "WM",
    "Method": "aCompCor",
    "Retained": true,
    "SingularValue": 61.1801079171,
    "VarianceExplained": 0.0147165432
  },
  "w_comp_cor_07": {
    "CumulativeVarianceExplained": 0.1541529833,
    "Mask": "WM",
    "Method": "aCompCor",
    "Retained": true,
    "SingularValue": 60.1148031894,
    "VarianceExplained": 0.0142084987
  },
  "w_comp_cor_08": {
    "CumulativeVarianceExplained": 0.1677907357,
    "Mask": "WM",
    "Method": "aCompCor",
    "Retained": true,
    "SingularValue": 58.8950416114,
    "VarianceExplained": 0.0136377523
  },
  "w_comp_cor_09": {
    "CumulativeVarianceExplained": 0.1811448656,
    "Mask": "WM",
    "Method": "aCompCor",
    "Retained": true,
    "SingularValue": 58.2794080391,
    "VarianceExplained": 0.0133541299
  },
  "w_comp_cor_10": {
    "CumulativeVarianceExplained": 0.1940995847,
    "Mask": "WM",
    "Method": "aCompCor",
    "Retained": true,
    "SingularValue": 57.4012479129,
    "VarianceExplained": 0.0129547191
  },
  "w_comp_cor_11": {
    "CumulativeVarianceExplained": 0.2068432346,
    "Mask": "WM",
    "Method": "aCompCor",
    "Retained": true,
    "SingularValue": 56.9317126333,
    "VarianceExplained": 0.0127436499
  },
  "w_comp_cor_12": {
    "CumulativeVarianceExplained": 0.2193489901,
    "Mask": "WM",
    "Method": "aCompCor",
    "Retained": true,
    "SingularValue": 56.3978179386,
    "VarianceExplained": 0.0125057556
  },
  "w_comp_cor_13": {
    "CumulativeVarianceExplained": 0.231502459,
    "Mask": "WM",
    "Method": "aCompCor",
    "Retained": true,
    "SingularValue": 55.5977812004,
    "VarianceExplained": 0.0121534689
  },
  "w_comp_cor_14": {
    "CumulativeVarianceExplained": 0.2436499229,
    "Mask": "WM",
    "Method": "aCompCor",
    "Retained": true,
    "SingularValue": 55.5840442286,
    "VarianceExplained": 0.0121474639
  },
  "w_comp_cor_15": {
    "CumulativeVarianceExplained": 0.2554267172,
    "Mask": "WM",
    "Method": "aCompCor",
    "Retained": true,
    "SingularValue": 54.729423997,
    "VarianceExplained": 0.0117767943
  },
  "w_comp_cor_16": {
    "CumulativeVarianceExplained": 0.2667980927,
    "Mask": "WM",
    "Method": "aCompCor",
    "Retained": true,
    "SingularValue": 53.7791378083,
    "VarianceExplained": 0.0113713756
  },
  "w_comp_cor_17": {
    "CumulativeVarianceExplained": 0.2780707597,
    "Mask": "WM",
    "Method": "aCompCor",
    "Retained": true,
    "SingularValue": 53.5452156016,
    "VarianceExplained": 0.011272667
  },
  "w_comp_cor_18": {
    "CumulativeVarianceExplained": 0.289167502,
    "Mask": "WM",
    "Method": "aCompCor",
    "Retained": true,
    "SingularValue": 53.1257512086,
    "VarianceExplained": 0.0110967423
  },
  "w_comp_cor_19": {
    "CumulativeVarianceExplained": 0.3000369628,
    "Mask": "WM",
    "Method": "aCompCor",
    "Retained": true,
    "SingularValue": 52.578880276,
    "VarianceExplained": 0.0108694608
  },
  "w_comp_cor_20": {
    "CumulativeVarianceExplained": 0.310828865,
    "Mask": "WM",
    "Method": "aCompCor",
    "Retained": true,
    "SingularValue": 52.3909573733,
    "VarianceExplained": 0.0107919022
  },
  "w_comp_cor_21": {
    "CumulativeVarianceExplained": 0.321381265,
    "Mask": "WM",
    "Method": "aCompCor",
    "Retained": true,
    "SingularValue": 51.8063451942,
    "VarianceExplained": 0.0105523999
  },
  "w_comp_cor_22": {
    "CumulativeVarianceExplained": 0.3318205948,
    "Mask": "WM",
    "Method": "aCompCor",
    "Retained": true,
    "SingularValue": 51.528042418,
    "VarianceExplained": 0.0104393299
  },
  "w_comp_cor_23": {
    "CumulativeVarianceExplained": 0.3420143929,
    "Mask": "WM",
    "Method": "aCompCor",
    "Retained": true,
    "SingularValue": 50.9184701274,
    "VarianceExplained": 0.0101937981
  },
  "w_comp_cor_24": {
    "CumulativeVarianceExplained": 0.3521985167,
    "Mask": "WM",
    "Method": "aCompCor",
    "Retained": true,
    "SingularValue": 50.8943027292,
    "VarianceExplained": 0.0101841238
  },
  "w_comp_cor_25": {
    "CumulativeVarianceExplained": 0.3622259284,
    "Mask": "WM",
    "Method": "aCompCor",
    "Retained": true,
    "SingularValue": 50.501206853,
    "VarianceExplained": 0.0100274117
  },
  "w_comp_cor_26": {
    "CumulativeVarianceExplained": 0.3722041515,
    "Mask": "WM",
    "Method": "aCompCor",
    "Retained": true,
    "SingularValue": 50.377189983,
    "VarianceExplained": 0.0099782231
  },
  "w_comp_cor_27": {
    "CumulativeVarianceExplained": 0.3821209182,
    "Mask": "WM",
    "Method": "aCompCor",
    "Retained": true,
    "SingularValue": 50.2218123092,
    "VarianceExplained": 0.0099167667
  },
  "w_comp_cor_28": {
    "CumulativeVarianceExplained": 0.3918120113,
    "Mask": "WM",
    "Method": "aCompCor",
    "Retained": true,
    "SingularValue": 49.6470805934,
    "VarianceExplained": 0.0096910931
  },
  "w_comp_cor_29": {
    "CumulativeVarianceExplained": 0.4013776565,
    "Mask": "WM",
    "Method": "aCompCor",
    "Retained": true,
    "SingularValue": 49.3247016972,
    "VarianceExplained": 0.0095656452
  },
  "w_comp_cor_30": {
    "CumulativeVarianceExplained": 0.4107734748,
    "Mask": "WM",
    "Method": "aCompCor",
    "Retained": true,
    "SingularValue": 48.8848895918,
    "VarianceExplained": 0.0093958183
  },
  "w_comp_cor_31": {
    "CumulativeVarianceExplained": 0.419989226,
    "Mask": "WM",
    "Method": "aCompCor",
    "Retained": true,
    "SingularValue": 48.4141938895,
    "VarianceExplained": 0.0092157512
  },
  "w_comp_cor_32": {
    "CumulativeVarianceExplained": 0.4291476933,
    "Mask": "WM",
    "Method": "aCompCor",
    "Retained": true,
    "SingularValue": 48.2634911595,
    "VarianceExplained": 0.0091584673
  },
  "w_comp_cor_33": {
    "CumulativeVarianceExplained": 0.4382383595,
    "Mask": "WM",
    "Method": "aCompCor",
    "Retained": true,
    "SingularValue": 48.0845092824,
    "VarianceExplained": 0.0090906662
  },
  "w_comp_cor_34": {
    "CumulativeVarianceExplained": 0.4472623772,
    "Mask": "WM",
    "Method": "aCompCor",
    "Retained": true,
    "SingularValue": 47.9079185098,
    "VarianceExplained": 0.0090240177
  },
  "w_comp_cor_35": {
    "CumulativeVarianceExplained": 0.4561728381,
    "Mask": "WM",
    "Method": "aCompCor",
    "Retained": true,
    "SingularValue": 47.6055316356,
    "VarianceExplained": 0.008910461
  },
  "w_comp_cor_36": {
    "CumulativeVarianceExplained": 0.4649913326,
    "Mask": "WM",
    "Method": "aCompCor",
    "Retained": true,
    "SingularValue": 47.3592218143,
    "VarianceExplained": 0.0088184945
  },
  "w_comp_cor_37": {
    "CumulativeVarianceExplained": 0.473795045,
    "Mask": "WM",
    "Method": "aCompCor",
    "Retained": true,
    "SingularValue": 47.3195119266,
    "VarianceExplained": 0.0088037124
  },
  "w_comp_cor_38": {
    "CumulativeVarianceExplained": 0.4825184242,
    "Mask": "WM",
    "Method": "aCompCor",
    "Retained": true,
    "SingularValue": 47.1031236935,
    "VarianceExplained": 0.0087233792
  },
  "w_comp_cor_39": {
    "CumulativeVarianceExplained": 0.4911770183,
    "Mask": "WM",
    "Method": "aCompCor",
    "Retained": true,
    "SingularValue": 46.9278894612,
    "VarianceExplained": 0.008658594
  },
  "w_comp_cor_40": {
    "CumulativeVarianceExplained": 0.4996200653,
    "Mask": "WM",
    "Method": "aCompCor",
    "Retained": true,
    "SingularValue": 46.340096879,
    "VarianceExplained": 0.008443047
  },
  "w_comp_cor_41": {
    "CumulativeVarianceExplained": 0.5079997476,
    "Mask": "WM",
    "Method": "aCompCor",
    "Retained": true,
    "SingularValue": 46.1658793163,
    "VarianceExplained": 0.0083796824
  }
}